pysegd3/__init__.py
pysegd3/readsegd3.py
pysegd3/readsegd3_as_obspy.py
pysegd3-1.1.0.data/scripts/readsegd3.py
pysegd3-1.1.0.data/scripts/readsegd3_as_obspy.py
pysegd3-1.1.0.dist-info/LICENSE
pysegd3-1.1.0.dist-info/METADATA
pysegd3-1.1.0.dist-info/WHEEL
pysegd3-1.1.0.dist-info/top_level.txt
pysegd3-1.1.0.dist-info/RECORD
