Metadata-Version: 2.1
Name: pysegd3
Version: 1.1.0
Author: Maximilien Lehujeur
Author-email: maximilien.lehujeur@univ-eiffel.fr
License: GPL3
Classifier: Programming Language :: Python :: 3
Classifier: Operating System :: POSIX :: Linux
Classifier: Operating System :: Microsoft :: Windows
Requires-Python: >=3.7
License-File: LICENSE
Requires-Dist: numpy
Requires-Dist: pytest
Requires-Dist: matplotlib
Requires-Dist: tempoo (>=1.1.0)
